{
  "nodes": [
    {"id": "Camilo Ortiz", "group": 1},
    {"id": "Python", "group": 2},
    {"id": "WordPress", "group": 2},
    {"id": "PHP", "group": 2},
    {"id": "Cistelsa", "group": 3},
    {"id": "COLVATEL S.A. E.S.P.", "group": 3},
    {"id": "Lean Startup", "group": 4},
    {"id": "Introducción al Metaverso", "group": 4},
    {"id": "Lógica de programación parte 2", "group": 4},
    {"id": "AWS Educate Introduction to Cloud", "group": 4},
    {"id": "Lógica de programación parte 1", "group": 4},
    {"id": "Henry Bootcamp", "group": 5},
    {"id": "Platzi Escuela de Blockchain", "group": 5},
    {"id": "Servicio Nacional de Aprendizaje (SENA)", "group": 6},
    {"id": "Colegio Superior de Telecomunicaciones", "group": 6}
  ],
  "links": [
    {"source": "Camilo Ortiz", "target": "Python", "value": 1},
    {"source": "Python", "target": "Henry Bootcamp", "value": 1},
    {"source": "Camilo Ortiz", "target": "WordPress", "value": 1},
    {"source": "WordPress", "target": "Cistelsa", "value": 1},
    {"source": "Camilo Ortiz", "target": "PHP", "value": 1},
    {"source": "PHP", "target": "Cistelsa", "value": 1},
    {"source": "Camilo Ortiz", "target": "Lean Startup", "value": 1},
    {"source": "Lean Startup", "target": "Cistelsa", "value": 1},
    {"source": "Camilo Ortiz", "target": "Introducción al Metaverso", "value": 1},
    {"source": "Introducción al Metaverso", "target": "Cistelsa", "value": 1},
    {"source": "Camilo Ortiz", "target": "Lógica de programación parte 2", "value": 1},
    {"source": "Lógica de programación parte 2", "target": "Cistelsa", "value": 1},
    {"source": "Camilo Ortiz", "target": "AWS Educate Introduction to Cloud", "value": 1},
    {"source": "AWS Educate Introduction to Cloud", "target": "Cistelsa", "value": 1},
    {"source": "Camilo Ortiz", "target": "Lógica de programación parte 1", "value": 1},
    {"source": "Lógica de programación parte 1", "target": "Cistelsa", "value": 1},
    {"source": "Camilo Ortiz", "target": "Henry Bootcamp", "value": 1},
    {"source": "Henry Bootcamp", "target": "Camilo Ortiz", "value": 1},
    {"source": "Camilo Ortiz", "target": "Platzi Escuela de Blockchain", "value": 1},
    {"source": "Platzi Escuela de Blockchain", "target": "Camilo Ortiz", "value": 1},
    {"source": "Camilo Ortiz", "target": "Servicio Nacional de Aprendizaje (SENA)", "value": 1},
    {"source": "Servicio Nacional de Aprendizaje (SENA)", "target": "Camilo Ortiz", "value": 1},
    {"source": "Camilo Ortiz", "target": "Colegio Superior de Telecomunicaciones", "value": 1},
    {"source": "Colegio Superior de Telecomunicaciones", "target": "Camilo Ortiz", "value": 1},
    {"source": "Cistelsa", "target": "Camilo Ortiz", "value": 1},
    {"source": "Cistelsa", "target": "Python", "value": 1},
    {"source": "Cistelsa", "target": "WordPress", "value": 1},
    {"source": "Cistelsa", "target": "PHP", "value": 1},
    {"source": "Cistelsa", "target": "Lean Startup", "value": 1},
    {"source": "Cistelsa", "target": "Introducción al Metaverso", "value": 1},
    {"source": "Cistelsa", "target": "Lógica de programación parte 2", "value": 1},
    {"source": "Cistelsa", "target": "AWS Educate Introduction to Cloud", "value": 1},
    {"source": "Cistelsa", "target": "Lógica de programación parte 1", "value": 1}
    ]
    }
